{
    "burstAmp_Fitness": {
        "Value": 12.232709215893909,
        "Fit": 555.5950288654005
    },
    "burst_peak_frequency_fitness": {
        "Value": 0.9661835748792271,
        "Fit": 44.57180344194965
    },
    "IBI_fitness": {
        "Value": 1860.0,
        "Fit": 1.768267051433735
    },
    "baseline_fitness": {
        "Value": 10.909212619822698,
        "Fit": 1000
    },
    "slopeFitness": {
        "Value": -0.06444351959823756,
        "Fit": 1.1375616170334146
    },
    "thresh": {
        "Value": 9.401007935293958,
        "Fit": 1000
    },
    "sustain_oscillation_fitness": {
        "Value": 20.674157303370784,
        "Fit": 1000
    },
    "E_rate_fitness": {
        "Value": 43.67460317460317,
        "Fit": 1000
    },
    "I_rate_fitness": {
        "Value": 23.84259259259259,
        "Fit": 1.85102722313369
    },
    "maxFitness": 1000,
    "average_fitness": 511.65818757766124,
    "average_scaled_fitness": 511.10203601919085
}