{
    "simConfig": {
        "E_L_mean": 18.8,
        "E_L_stdev": 0.19276853595469046,
        "E_Ra_mean": 128.0,
        "E_Ra_stdev": 5.9285289964037915,
        "E_diam_mean": 18.8,
        "E_diam_stdev": 4.846773602858891,
        "I_L_mean": 9.0,
        "I_L_stdev": 0.33950920499932136,
        "I_Ra_mean": 110.0,
        "I_Ra_stdev": 36.65697461273874,
        "I_diam_mean": 10.0,
        "I_diam_stdev": 1.949557813146261,
        "addSynMechs": true,
        "allowConnsWithWeight0": true,
        "allowSelfConns": false,
        "analysis": {},
        "backupCfgFile": [],
        "cache_efficient": true,
        "checkErrors": false,
        "compactConnFormat": false,
        "connRandomSecFromList": true,
        "coreneuron": false,
        "createNEURONObj": true,
        "createPyStruct": true,
        "cvode_active": false,
        "cvode_atol": 0.001,
        "distributeSynsUniformly": true,
        "dt": 0.025,
        "dump_coreneuron_model": false,
        "duration": 1000.0,
        "duration_seconds": 60.0,
        "filename": "model_output",
        "gatherOnlySimData": false,
        "gkbar_E": 0.35937212825034004,
        "gkbar_E_std": 0.3016938206901107,
        "gkbar_I": 0.12889282974779315,
        "gkbar_I_std": 0.11755925301341287,
        "gnabar_E": 1.493775984975095,
        "gnabar_E_std": 0.10007047961068283,
        "gnabar_I": 2.98764311437503,
        "gnabar_I_std": 0.34794947975777124,
        "gpu": false,
        "hParams": {
            "celsius": 6.3,
            "clamp_resist": 0.001,
            "v_init": -65.0
        },
        "includeParamsLabel": true,
        "invertedYCoord": true,
        "networkType": "22May24",
        "oneSynPerNetcon": true,
        "printPopAvgRates": [
            100,
            1000.0
        ],
        "printRunTime": false,
        "printSynsAfterRule": false,
        "probEE": 0.9760376644434744,
        "probEE_std": 0.001551756912314798,
        "probEI": 0.9592537912563949,
        "probEI_std": 0.11206777124695547,
        "probIE": 0.9991084836279894,
        "probIE_std": 0.2288241576628243,
        "probII": 0.23086694972689203,
        "probII_std": 0.31283684440316917,
        "probLengthConst": 74.49588009762056,
        "propVelocity": 1.0,
        "pt3dRelativeToCellLocation": true,
        "rand123GlobalIndex": null,
        "random123": false,
        "recordCells": [
            [
                "E",
                [
                    16,
                    79
                ]
            ],
            [
                "I",
                [
                    28,
                    1
                ]
            ]
        ],
        "recordCellsSpikes": -1,
        "recordDipole": false,
        "recordDipolesHNN": false,
        "recordLFP": [],
        "recordStep": 0.1,
        "recordStim": false,
        "recordTime": true,
        "recordTraces": {
            "soma_voltage": {
                "loc": 0.5,
                "sec": "soma",
                "var": "v"
            }
        },
        "saveCSV": false,
        "saveCellConns": true,
        "saveCellSecs": true,
        "saveDat": false,
        "saveDataInclude": [
            "simData",
            "simConfig",
            "netParams",
            "net"
        ],
        "saveDipoleCells": false,
        "saveDipolePops": false,
        "saveDpk": false,
        "saveFolder": "/pscratch/sd/a/adammwea/2DNetworkSimulations/NERSC/output/240527_Run3_this_should_work/gen_12",
        "saveHDF5": false,
        "saveJson": true,
        "saveLFPCells": false,
        "saveLFPPops": false,
        "saveMat": false,
        "savePickle": false,
        "saveTiming": false,
        "seeds": {
            "cell": 1,
            "conn": 1,
            "loc": 1,
            "stim": 1
        },
        "simLabel": "gen_12_cand_39",
        "tau1_exc": 3.8190816089581174,
        "tau1_exc_std": 0.001023101473098456,
        "tau1_inh": 3.251499937309518,
        "tau1_inh_std": 1.7943065392507624,
        "tau2_exc": 17.43193284098528,
        "tau2_exc_std": 6.665576870615999,
        "tau2_inh": 18.208351958024284,
        "tau2_inh_std": 0.38706095005717867,
        "timestampFilename": false,
        "timing": true,
        "tstop": 1000.0,
        "use_fast_imem": false,
        "validateNetParams": false,
        "verbose": false,
        "weightEE": 0.8760345204841868,
        "weightEE_std": 0.13981468929060303,
        "weightEI": 0.26739326929970525,
        "weightEI_std": 0.06337181165371662,
        "weightIE": 0.9057564362093531,
        "weightIE_std": 0.24276861311071082,
        "weightII": 0.39382544547172593,
        "weightII_std": 0.0192133002824951
    }
}