{
    "simConfig": {
        "Erhythmic_stimWeight": 0.003730435240632853,
        "Irhythmic_stimWeight": 0.01813780316816051,
        "addSynMechs": true,
        "allowConnsWithWeight0": true,
        "allowSelfConns": false,
        "analysis": {},
        "backupCfgFile": [],
        "cache_efficient": true,
        "checkErrors": false,
        "compactConnFormat": false,
        "connRandomSecFromList": true,
        "coreneuron": false,
        "createNEURONObj": true,
        "createPyStruct": true,
        "cvode_active": false,
        "cvode_atol": 0.001,
        "distributeSynsUniformly": true,
        "dt": 0.025,
        "dump_coreneuron_model": false,
        "duration": 1000.0,
        "duration_seconds": 5.0,
        "filename": "model_output",
        "gatherOnlySimData": false,
        "gkbar_E": 0.060085609189408085,
        "gkbar_I": 0.4362294270893142,
        "gnabar_E": 3.6951966099612186,
        "gnabar_I": 1.2905427579640638,
        "gpu": false,
        "hParams": {
            "celsius": 6.3,
            "clamp_resist": 0.001,
            "v_init": -65.0
        },
        "includeParamsLabel": true,
        "invertedYCoord": true,
        "networkType": "pre13Apr24",
        "oneSynPerNetcon": true,
        "printPopAvgRates": [
            100,
            1000.0
        ],
        "printRunTime": false,
        "printSynsAfterRule": false,
        "probEE": 0.4014074767230807,
        "probEI": 0.36490702328946434,
        "probIE": 0.9764947463816922,
        "probII": 0.9686959548416393,
        "probLengthConst": 1947.5062036528698,
        "propVelocity": 1.0,
        "pt3dRelativeToCellLocation": true,
        "rand123GlobalIndex": null,
        "random123": false,
        "recordCells": [
            [
                "E",
                [
                    0
                ]
            ],
            [
                "I",
                [
                    0
                ]
            ]
        ],
        "recordCellsSpikes": -1,
        "recordDipole": false,
        "recordDipolesHNN": false,
        "recordLFP": [],
        "recordStep": 0.1,
        "recordStim": false,
        "recordTime": true,
        "recordTraces": {
            "soma_voltage": {
                "loc": 0.5,
                "sec": "soma",
                "var": "v"
            }
        },
        "rythmic_stiminterval": 4987.1699609302805,
        "rythmic_stimnoise": 0.10629505755411087,
        "saveCSV": false,
        "saveCellConns": true,
        "saveCellSecs": true,
        "saveDat": false,
        "saveDataInclude": [
            "simData",
            "simConfig",
            "netParams",
            "net"
        ],
        "saveDipoleCells": false,
        "saveDipolePops": false,
        "saveDpk": false,
        "saveFolder": "/pscratch/sd/a/adammwea/2DNetworkSimulations/NERSC/output/240426_Run12_26AprSAFE_1x100/gen_5",
        "saveHDF5": false,
        "saveJson": true,
        "saveLFPCells": false,
        "saveLFPPops": false,
        "saveMat": false,
        "savePickle": false,
        "saveTiming": false,
        "seeds": {
            "cell": 1,
            "conn": 1,
            "loc": 1,
            "stim": 1
        },
        "simLabel": "gen_5_cand_10",
        "tau1_exc": 1.3416539150196216,
        "tau1_inh": 0.9151729406563859,
        "tau2_exc": 3.89555590468767,
        "tau2_inh": 6.7962590283829885,
        "timestampFilename": false,
        "timing": true,
        "tstop": 1000.0,
        "use_fast_imem": false,
        "validateNetParams": false,
        "verbose": false,
        "weightEE": 0.04693839610757343,
        "weightEI": 0.09291596436092803,
        "weightIE": 0.003123665470784175,
        "weightII": 0.015293696309321848
    }
}