{
    "simConfig": {
        "E_L_mean": 18.8,
        "E_L_stdev": 7.905600660686989,
        "E_Ra_mean": 128.0,
        "E_Ra_stdev": 49.91338815374539,
        "E_diam_mean": 18.8,
        "E_diam_stdev": 2.1075213442641703,
        "I_L_mean": 9.0,
        "I_L_stdev": 0.3326510254202398,
        "I_Ra_mean": 110.0,
        "I_Ra_stdev": 46.32393302033515,
        "I_diam_mean": 10.0,
        "I_diam_stdev": 0.8919432959912036,
        "addSynMechs": true,
        "allowConnsWithWeight0": true,
        "allowSelfConns": false,
        "analysis": {},
        "backupCfgFile": [],
        "cache_efficient": true,
        "checkErrors": false,
        "compactConnFormat": false,
        "connRandomSecFromList": true,
        "coreneuron": false,
        "createNEURONObj": true,
        "createPyStruct": true,
        "cvode_active": false,
        "cvode_atol": 0.001,
        "distributeSynsUniformly": true,
        "dt": 0.025,
        "dump_coreneuron_model": false,
        "duration": 1000.0,
        "duration_seconds": 330.0,
        "filename": "model_output",
        "gatherOnlySimData": false,
        "gkbar_E": 0.7444761626097203,
        "gkbar_E_std": 0.329732622906228,
        "gkbar_I": 8.098263317960697,
        "gkbar_I_std": 0.1011211582993232,
        "gnabar_E": 2.38664253846761,
        "gnabar_E_std": 1.2863678758906665,
        "gnabar_I": 0.20106245057545014,
        "gnabar_I_std": 0.8414407413393515,
        "gpu": false,
        "hParams": {
            "celsius": 6.3,
            "clamp_resist": 0.001,
            "v_init": -65.0
        },
        "includeParamsLabel": true,
        "invertedYCoord": true,
        "networkType": "22May24",
        "oneSynPerNetcon": true,
        "printPopAvgRates": [
            100,
            1000.0
        ],
        "printRunTime": false,
        "printSynsAfterRule": false,
        "probEE": 0.27711745516027275,
        "probEE_std": 0.4684048132711672,
        "probEI": 0.35276778393734093,
        "probEI_std": 0.029774735049767798,
        "probIE": 0.10396010566300856,
        "probIE_std": 0.43932867636960327,
        "probII": 0.2515017751848838,
        "probII_std": 0.12303082678999183,
        "probLengthConst": 2989.266280228483,
        "propVelocity": 1.0,
        "pt3dRelativeToCellLocation": true,
        "rand123GlobalIndex": null,
        "random123": false,
        "recordCells": [
            [
                "E",
                [
                    68,
                    13
                ]
            ],
            [
                "I",
                [
                    4,
                    5
                ]
            ]
        ],
        "recordCellsSpikes": -1,
        "recordDipole": false,
        "recordDipolesHNN": false,
        "recordLFP": [],
        "recordStep": 0.1,
        "recordStim": false,
        "recordTime": true,
        "recordTraces": {
            "soma_voltage": {
                "loc": 0.5,
                "sec": "soma",
                "var": "v"
            }
        },
        "saveCSV": false,
        "saveCellConns": true,
        "saveCellSecs": true,
        "saveDat": false,
        "saveDataInclude": [
            "simData",
            "simConfig",
            "netParams",
            "net"
        ],
        "saveDipoleCells": false,
        "saveDipolePops": false,
        "saveDpk": false,
        "saveFolder": "/pscratch/sd/a/adammwea/2DNetworkSimulations/NERSC/output/240604_Run1_24n24hr/gen_1",
        "saveHDF5": false,
        "saveJson": true,
        "saveLFPCells": false,
        "saveLFPPops": false,
        "saveMat": false,
        "savePickle": false,
        "saveTiming": false,
        "seeds": {
            "cell": 1,
            "conn": 1,
            "loc": 1,
            "stim": 1
        },
        "simLabel": "gen_1_cand_271",
        "tau1_exc": 0.3392534384735113,
        "tau1_exc_std": 0.9754021829688284,
        "tau1_inh": 8.118997020688514,
        "tau1_inh_std": 1.6351192619226513,
        "tau2_exc": 10.890544966386164,
        "tau2_exc_std": 1.6308936337157305,
        "tau2_inh": 9.386989447237166,
        "tau2_inh_std": 8.847595331039365,
        "timestampFilename": false,
        "timing": true,
        "tstop": 1000.0,
        "use_fast_imem": false,
        "validateNetParams": false,
        "verbose": false,
        "weightEE": 1.6247209369741995,
        "weightEE_std": 0.3844950827019752,
        "weightEI": 0.09409653273793717,
        "weightEI_std": 0.1114100034286165,
        "weightIE": 0.08081771419809503,
        "weightIE_std": 0.06815552303914264,
        "weightII": 1.3901878334693243,
        "weightII_std": 0.24866388463284408
    }
}