{
    "E_rate_fit": {
        "Value": 16.090482970190184,
        "Fit": 615.6816443956269,
        "Features": {
            "E_rate_mean": 16.090482970190184,
            "E_rate_fitness": 840.1601569798055,
            "stdev": 28.753569801485657,
            "stdev_fitness": 1000,
            "kurtosis": 9.0117374583161,
            "kurtosis_fitness": 1000,
            "skewness": 2.947312627233388,
            "skew_fitness": 6.884776207075529,
            "fitness": 615.6816443956269
        }
    },
    "I_rate_fit": {
        "Value": 4.399825264849479,
        "Fit": 567.8092736199918,
        "Features": {
            "I_rate_mean": 4.399825264849479,
            "I_rate_fitness": 697.9769465365525,
            "stdev": 7.770819769438827,
            "stdev_fitness": 202.8591642899829,
            "kurtosis": 11.129075836654335,
            "kurtosis_fitness": 1000,
            "skewness": 3.1368709335382654,
            "skew_fitness": 5.450874323422839,
            "fitness": 567.8092736199918
        }
    },
    "E_ISI_fit": {
        "Value": 5.816642127680356,
        "Fit": 796.355932087673,
        "Features": {
            "E_ISI_mean": 5.816642127680356,
            "E_ISI_fitness": 840.1601678246162,
            "stdev": 16.08397639176808,
            "stdev_fitness": 1000,
            "kurtosis": 54.37009389160994,
            "kurtosis_fitness": 1000,
            "skewness": 6.772533907367812,
            "skew_fitness": 548.9076284384026,
            "fitness": 796.355932087673
        }
    },
    "I_ISI_fit": {
        "Value": 8.69170493914608,
        "Fit": 229.49132015269302,
        "Features": {
            "I_ISI_mean": 8.69170493914608,
            "I_ISI_fitness": 605.046986590288,
            "stdev": 13.879823801250035,
            "stdev_fitness": 1000,
            "kurtosis": 3.3447357309335013,
            "kurtosis_fitness": 78.19516979472077,
            "skewness": 1.9989446396046897,
            "skew_fitness": 5.231804073070342,
            "fitness": 229.49132015269302
        }
    },
    "baseline_fit": {
        "Value": 722.2866547335886,
        "Fit": 1000
    },
    "IBI_fitness": {
        "Value": null,
        "Fit": 1000,
        "deprioritized": true
    },
    "burst_frequency_fitness": {
        "Value": null,
        "Fit": 1000,
        "deprioritized": true
    },
    "big_burst_fit": {
        "Value": null,
        "Fit": 1000,
        "deprioritized": true
    },
    "small_burst_fit": {
        "Value": null,
        "Fit": 1000,
        "deprioritized": true
    },
    "thresh_fit": {
        "Value": 1446.4852926576837,
        "Fit": 1000,
        "deprioritized": true
    },
    "bimodal_burst_fit": {
        "Value": null,
        "Fit": 1000,
        "deprioritized": true
    },
    "slope_fit": {
        "Value": 8.438163489351835e-05,
        "Fit": 1000,
        "deprioritized": true
    },
    "maxFitness": 1000,
    "average_fitness": 850.7781808546655,
    "average_scaled_fitness": 0.8063333703458003
}