{
    "simConfig": {
        "Erhythmic_stimWeight": 0.01118952384134422,
        "Irhythmic_stimWeight": 0.015597287025658413,
        "addSynMechs": true,
        "allowConnsWithWeight0": true,
        "allowSelfConns": false,
        "analysis": {},
        "backupCfgFile": [],
        "cache_efficient": true,
        "checkErrors": false,
        "compactConnFormat": false,
        "connRandomSecFromList": true,
        "coreneuron": false,
        "createNEURONObj": true,
        "createPyStruct": true,
        "cvode_active": false,
        "cvode_atol": 0.001,
        "distributeSynsUniformly": true,
        "dt": 0.025,
        "dump_coreneuron_model": false,
        "duration": 1000.0,
        "duration_seconds": 5.0,
        "filename": "model_output",
        "gatherOnlySimData": false,
        "gkbar_E": 0.3278764271283053,
        "gkbar_I": 1.7816022686639879,
        "gnabar_E": 2.756284923893312,
        "gnabar_I": 0.597918289006401,
        "gpu": false,
        "hParams": {
            "celsius": 6.3,
            "clamp_resist": 0.001,
            "v_init": -65.0
        },
        "includeParamsLabel": true,
        "invertedYCoord": true,
        "networkType": "pre13Apr24",
        "oneSynPerNetcon": true,
        "printPopAvgRates": [
            100,
            1000.0
        ],
        "printRunTime": false,
        "printSynsAfterRule": false,
        "probEE": 0.1826902139046256,
        "probEI": 0.6182164336345692,
        "probIE": 0.21335516381013897,
        "probII": 0.12415754911469132,
        "probLengthConst": 72.72283716589179,
        "propVelocity": 1.0,
        "pt3dRelativeToCellLocation": true,
        "rand123GlobalIndex": null,
        "random123": false,
        "recordCells": [],
        "recordCellsSpikes": -1,
        "recordDipole": false,
        "recordDipolesHNN": false,
        "recordLFP": [],
        "recordStep": 0.1,
        "recordStim": false,
        "recordTime": true,
        "recordTraces": {
            "soma_voltage": {
                "loc": 0.5,
                "sec": "soma",
                "var": "v"
            }
        },
        "rythmic_stiminterval": 257.968186337906,
        "rythmic_stimnoise": 0.19406926257931065,
        "saveCSV": false,
        "saveCellConns": true,
        "saveCellSecs": true,
        "saveDat": false,
        "saveDataInclude": [
            "simData",
            "simConfig",
            "netParams",
            "net"
        ],
        "saveDipoleCells": false,
        "saveDipolePops": false,
        "saveDpk": false,
        "saveFolder": "/pscratch/sd/a/adammwea/2DNetworkSimulations/NERSC/output/240425_Run3_overnightRun24Apr_1x128/gen_2",
        "saveHDF5": false,
        "saveJson": true,
        "saveLFPCells": false,
        "saveLFPPops": false,
        "saveMat": false,
        "savePickle": false,
        "saveTiming": false,
        "seeds": {
            "cell": 1,
            "conn": 1,
            "loc": 1,
            "stim": 1
        },
        "simLabel": "gen_2_cand_104",
        "tau1_exc": 0.8,
        "tau1_inh": 0.8,
        "tau2_exc": 6.0,
        "tau2_inh": 9.0,
        "timestampFilename": false,
        "timing": true,
        "tstop": 1000.0,
        "use_fast_imem": false,
        "validateNetParams": false,
        "verbose": false,
        "weightEE": 0.09511562648720825,
        "weightEI": 0.08263555054371811,
        "weightIE": 0.09432400643123923,
        "weightII": 0.06299022948851586
    }
}