{
    "burstAmp_Fitness": {
        "Value": 0.3643801270884133,
        "Fit": 1000.0
    },
    "burst_peak_frequency_fitness": {
        "Value": 0.41928721174004197,
        "Fit": 1.6748494329161001
    },
    "IBI_fitness": {
        "Value": 4200.0,
        "Fit": 1000.0
    },
    "baseline_fitness": {
        "Value": 11.045639724436596,
        "Fit": 1000
    },
    "slopeFitness": {
        "Value": 0.005866634551813446,
        "Fit": 1.0118023739162028
    },
    "thresh": {
        "Value": 10.829419683737287,
        "Fit": 1000
    },
    "sustain_oscillation_fitness": {
        "Value": 89.88095238095238,
        "Fit": 7.567097131370448
    },
    "rate_fitness": {
        "Value": 21.68320105820106,
        "Fit": 503.6604773418542
    },
    "maxFitness": 1000,
    "average_fitness": 564.239278285007,
    "average_scaled_fitness": 563.7979279930432
}