{
    "simConfig": {
        "addSynMechs": true,
        "allowConnsWithWeight0": true,
        "allowSelfConns": false,
        "analysis": {},
        "backupCfgFile": [],
        "cache_efficient": true,
        "checkErrors": false,
        "compactConnFormat": false,
        "connRandomSecFromList": true,
        "coreneuron": false,
        "createNEURONObj": true,
        "createPyStruct": true,
        "cvode_active": false,
        "cvode_atol": 0.001,
        "distributeSynsUniformly": true,
        "dt": 0.025,
        "dump_coreneuron_model": false,
        "duration": 1000.0,
        "duration_seconds": 15.0,
        "filename": "model_output",
        "gatherOnlySimData": false,
        "gkbar_E": 0.6708949772533188,
        "gkbar_I": 0.3422466103881273,
        "gnabar_E": 4.752475466943194,
        "gnabar_I": 0.6905281296958945,
        "gpu": false,
        "hParams": {
            "celsius": 6.3,
            "clamp_resist": 0.001,
            "v_init": -65.0
        },
        "includeParamsLabel": true,
        "invertedYCoord": true,
        "networkType": "pre13Apr24",
        "oneSynPerNetcon": true,
        "printPopAvgRates": [
            100,
            1000.0
        ],
        "printRunTime": false,
        "printSynsAfterRule": false,
        "probEE": 0.7554805596188132,
        "probEI": 0.1342548072158513,
        "probIE": 0.1730816251349813,
        "probII": 0.028633943366242406,
        "probLengthConst": 2452.120058073825,
        "propVelocity": 1.0,
        "pt3dRelativeToCellLocation": true,
        "rand123GlobalIndex": null,
        "random123": false,
        "recordCells": [
            [
                "E",
                [
                    276,
                    1
                ]
            ],
            [
                "I",
                [
                    99,
                    102
                ]
            ]
        ],
        "recordCellsSpikes": -1,
        "recordDipole": false,
        "recordDipolesHNN": false,
        "recordLFP": [],
        "recordStep": 0.1,
        "recordStim": false,
        "recordTime": true,
        "recordTraces": {},
        "saveCSV": false,
        "saveCellConns": true,
        "saveCellSecs": true,
        "saveDat": false,
        "saveDataInclude": [
            "simData",
            "simConfig",
            "netParams",
            "net"
        ],
        "saveDipoleCells": false,
        "saveDipolePops": false,
        "saveDpk": false,
        "saveFolder": "/pscratch/sd/a/adammwea/2DNetworkSimulations/NERSC/output/240521_Run2_overnight_reg/gen_2",
        "saveHDF5": false,
        "saveJson": true,
        "saveLFPCells": false,
        "saveLFPPops": false,
        "saveMat": false,
        "savePickle": false,
        "saveTiming": false,
        "seeds": {
            "cell": 1,
            "conn": 1,
            "loc": 1,
            "stim": 1
        },
        "simLabel": "gen_2_cand_32",
        "tau1_exc": 7.80217538786616,
        "tau1_inh": 2.9452427163201853,
        "tau2_exc": 15.080227390616248,
        "tau2_inh": 8.697865692943687,
        "timestampFilename": false,
        "timing": true,
        "tstop": 1000.0,
        "use_fast_imem": false,
        "validateNetParams": false,
        "verbose": false,
        "weightEE": 0.014600906140331597,
        "weightEI": 0.09420976016044416,
        "weightIE": 0.028596934249919114,
        "weightII": 0.16491840828275667
    }
}