{
    "simConfig": {
        "E_L_mean": 18.8,
        "E_L_stdev": 3.000647905603853,
        "E_Ra_mean": 128.0,
        "E_Ra_stdev": 46.17848982574975,
        "E_diam_mean": 18.8,
        "E_diam_stdev": 3.657442162854948,
        "I_L_mean": 9.0,
        "I_L_stdev": 0.4766311888295034,
        "I_Ra_mean": 110.0,
        "I_Ra_stdev": 5.485863323309703,
        "I_diam_mean": 10.0,
        "I_diam_stdev": 1.0699828396506077,
        "addSynMechs": true,
        "allowConnsWithWeight0": true,
        "allowSelfConns": false,
        "analysis": {},
        "backupCfgFile": [],
        "cache_efficient": true,
        "checkErrors": false,
        "compactConnFormat": false,
        "connRandomSecFromList": true,
        "coreneuron": false,
        "createNEURONObj": true,
        "createPyStruct": true,
        "cvode_active": false,
        "cvode_atol": 0.001,
        "distributeSynsUniformly": true,
        "dt": 0.025,
        "dump_coreneuron_model": false,
        "duration": 1000.0,
        "duration_seconds": 90.0,
        "filename": "model_output",
        "gatherOnlySimData": false,
        "gkbar_E": 0.978395819668337,
        "gkbar_E_std": 0.45180185172482834,
        "gkbar_I": 3.226800856113719,
        "gkbar_I_std": 1.5344717429932655,
        "gnabar_E": 6.524560213367863,
        "gnabar_E_std": 1.657199229644483,
        "gnabar_I": 0.3932251632827888,
        "gnabar_I_std": 0.9963004903678201,
        "gpu": false,
        "hParams": {
            "celsius": 6.3,
            "clamp_resist": 0.001,
            "v_init": -65.0
        },
        "includeParamsLabel": true,
        "invertedYCoord": true,
        "networkType": "22May24",
        "oneSynPerNetcon": true,
        "printPopAvgRates": [
            100,
            1000.0
        ],
        "printRunTime": false,
        "printSynsAfterRule": false,
        "probEE": 0.3390819628442626,
        "probEE_std": 0.4096627515844526,
        "probEI": 0.37431544424712404,
        "probEI_std": 0.049215514412997666,
        "probIE": 0.33153078151109105,
        "probIE_std": 0.0018189046511163653,
        "probII": 0.0036920498435215002,
        "probII_std": 0.44419467077879987,
        "probLengthConst": 222.02157660783655,
        "propVelocity": 1.0,
        "pt3dRelativeToCellLocation": true,
        "rand123GlobalIndex": null,
        "random123": false,
        "recordCells": [
            [
                "E",
                [
                    74,
                    47
                ]
            ],
            [
                "I",
                [
                    38,
                    3
                ]
            ]
        ],
        "recordCellsSpikes": -1,
        "recordDipole": false,
        "recordDipolesHNN": false,
        "recordLFP": [],
        "recordStep": 0.1,
        "recordStim": false,
        "recordTime": true,
        "recordTraces": {
            "soma_voltage": {
                "loc": 0.5,
                "sec": "soma",
                "var": "v"
            }
        },
        "saveCSV": false,
        "saveCellConns": true,
        "saveCellSecs": true,
        "saveDat": false,
        "saveDataInclude": [
            "simData",
            "simConfig",
            "netParams",
            "net"
        ],
        "saveDipoleCells": false,
        "saveDipolePops": false,
        "saveDpk": false,
        "saveFolder": "/pscratch/sd/a/adammwea/2DNetworkSimulations/NERSC/output/240528_Run1_this_does_work/gen_7",
        "saveHDF5": false,
        "saveJson": true,
        "saveLFPCells": false,
        "saveLFPPops": false,
        "saveMat": false,
        "savePickle": false,
        "saveTiming": false,
        "seeds": {
            "cell": 1,
            "conn": 1,
            "loc": 1,
            "stim": 1
        },
        "simLabel": "gen_7_cand_5",
        "tau1_exc": 2.4934145846878826,
        "tau1_exc_std": 1.49656206842356,
        "tau1_inh": 2.799472245538171,
        "tau1_inh_std": 0.011721033707727369,
        "tau2_exc": 12.291180686995553,
        "tau2_exc_std": 2.099169582942389,
        "tau2_inh": 6.333715020762003,
        "tau2_inh_std": 8.033415839609267,
        "timestampFilename": false,
        "timing": true,
        "tstop": 1000.0,
        "use_fast_imem": false,
        "validateNetParams": false,
        "verbose": false,
        "weightEE": 0.4123291155355765,
        "weightEE_std": 0.0009609620141949935,
        "weightEI": 0.7802014376590337,
        "weightEI_std": 0.09140745421427016,
        "weightIE": 0.9211286638347356,
        "weightIE_std": 0.18330666614702457,
        "weightII": 1.307100557070975,
        "weightII_std": 0.19408634636706307
    }
}