{
    "E_rate_fit": {
        "Value": 25.86192231749449,
        "Fit": 322.23216534782046,
        "Features": {
            "E_rate_mean": 25.86192231749449,
            "E_rate_fitness": 750.2502079067018,
            "stdev": 35.922561331818194,
            "stdev_fitness": 1000,
            "kurtosis": 5.457558022537352,
            "kurtosis_fitness": 213.2697982312882,
            "skewness": 2.173776783841675,
            "skew_fitness": 3.1764899054714015,
            "fitness": 322.23216534782046
        }
    },
    "I_rate_fit": {
        "Value": 12.604385944997098,
        "Fit": 637.3574987773493,
        "Features": {
            "I_rate_mean": 12.604385944997098,
            "I_rate_fitness": 900.1001854491493,
            "stdev": 29.383275997486834,
            "stdev_fitness": 1000,
            "kurtosis": 13.912470556539034,
            "kurtosis_fitness": 1000,
            "skewness": 3.9236914685662763,
            "skew_fitness": 11.972310882898658,
            "fitness": 637.3574987773493
        }
    },
    "E_ISI_fit": {
        "Value": 1.6788490424017335,
        "Fit": 619.538735788274,
        "Features": {
            "E_ISI_mean": 1.6788490424017335,
            "E_ISI_fitness": 750.2502693692533,
            "stdev": 4.330406458911248,
            "stdev_fitness": 39.71405571686145,
            "kurtosis": 28.851992795712817,
            "kurtosis_fitness": 1000,
            "skewness": 5.150117548718524,
            "skew_fitness": 108.36593799556876,
            "fitness": 619.538735788274
        }
    },
    "I_ISI_fit": {
        "Value": 7.551797228533095,
        "Fit": 620.088641209276,
        "Features": {
            "I_ISI_mean": 7.551797228533095,
            "I_ISI_fitness": 850.1502530114298,
            "stdev": 11.15103216130882,
            "stdev_fitness": 1000,
            "kurtosis": 6.157559284436804,
            "kurtosis_fitness": 1000,
            "skewness": 2.6582742415797003,
            "skew_fitness": 10.115670616398399,
            "fitness": 620.088641209276
        }
    },
    "baseline_fit": {
        "Value": 970.156119602216,
        "Fit": 1000
    },
    "IBI_fitness": {
        "Value": null,
        "Fit": 1000,
        "deprioritized": true
    },
    "burst_frequency_fitness": {
        "Value": 0.011111111111111112,
        "Fit": 1000,
        "deprioritized": true
    },
    "big_burst_fit": {
        "Value": 2113.5732780321428,
        "Fit": 1000,
        "features": {
            "StdDev": 0.0,
            "Kurtosis": NaN,
            "Skewness": NaN,
            "StdDevFit": 1000,
            "KurtosisFit": 1000,
            "SkewnessFit": 1000
        },
        "deprioritized": true
    },
    "small_burst_fit": {
        "Value": null,
        "Fit": 1000,
        "deprioritized": true
    },
    "thresh_fit": {
        "Value": 1951.2685998613981,
        "Fit": 1000,
        "deprioritized": true
    },
    "bimodal_burst_fit": {
        "Value": null,
        "Fit": 1000,
        "deprioritized": true
    },
    "slope_fit": {
        "Value": -0.018765732473588294,
        "Fit": 1000,
        "deprioritized": true
    },
    "maxFitness": 1000,
    "average_fitness": 849.9347534268933,
    "average_scaled_fitness": 0.778589011014195
}