{
    "burstAmp_Fitness": {
        "Value": 11.04559921499785,
        "Fit": 7.222494504711121
    },
    "burst_peak_frequency_fitness": {
        "Value": 0.641025641025641,
        "Fit": 6.3354056581195
    },
    "IBI_fitness": {
        "Value": null,
        "Fit": 1000
    },
    "baseline_fitness": {
        "Value": 24.24098145105679,
        "Fit": 1000
    },
    "slopeFitness": {
        "Value": -0.03822746970362056,
        "Fit": 1.0794535484245094
    },
    "thresh": {
        "Value": 18.431499999866862,
        "Fit": 1000
    },
    "sustain_oscillation_fitness": {
        "Value": 13.134328358208954,
        "Fit": 1000
    },
    "rate_fitness": {
        "Value": 46.16600529100529,
        "Fit": 503.73926794814315
    },
    "maxFitness": 1000,
    "average_fitness": 564.7970777074247,
    "average_scaled_fitness": 564.3267887135481
}