{
    "burstAmp_Fitness": {
        "Value": 1.1090006849570209,
        "Fit": 1000.0
    },
    "burst_peak_frequency_fitness": {
        "Value": 0.21097046413502107,
        "Fit": 1000
    },
    "IBI_fitness": {
        "Value": null,
        "Fit": 1000
    },
    "baseline_fitness": {
        "Value": 17.849995663463794,
        "Fit": 1000
    },
    "slopeFitness": {
        "Value": 0.005638201499183856,
        "Fit": 1.0113402212853144
    },
    "thresh": {
        "Value": 16.96792562496275,
        "Fit": 1000
    },
    "sustain_oscillation_fitness": {
        "Value": 73.05389221556887,
        "Fit": 1000
    },
    "rate_fitness": {
        "Value": 29.6005291005291,
        "Fit": 503.5569016983662
    },
    "maxFitness": 1000,
    "average_fitness": 813.0710302399565,
    "average_scaled_fitness": 812.8817900681174
}