{
    "E_rate_fit": {
        "Value": 50.05602905197939,
        "Fit": 1000.0,
        "Features": {
            "E_rate_mean": 50.05602905197939,
            "E_rate_fitness": 1000.0,
            "stdev": 11.75564072455861,
            "stdev_fitness": 1000,
            "kurtosis": -0.06530258157543178,
            "kurtosis_fitness": 1000,
            "skewness": -0.3606558045072281,
            "skew_fitness": 1000,
            "fitness": 1000.0
        }
    },
    "I_rate_fit": {
        "Value": null,
        "Fit": 1000
    },
    "E_ISI_fit": {
        "Value": 0.020746488170834923,
        "Fit": 1000.0,
        "Features": {
            "E_ISI_mean": 0.020746488170834923,
            "E_ISI_fitness": 1000.0,
            "stdev": 0.003292586566083527,
            "stdev_fitness": 1000,
            "kurtosis": -0.8055865030764147,
            "kurtosis_fitness": 1000,
            "skewness": -0.9485707458455727,
            "skew_fitness": 1000,
            "fitness": 1000.0
        }
    },
    "I_ISI_fit": {
        "Value": null,
        "Fit": 1000
    },
    "baseline_fit": {
        "Value": 745.1462320118693,
        "Fit": 1000,
        "deprioritized": true
    },
    "IBI_fitness": {
        "Value": null,
        "Fit": 1000,
        "deprioritized": true
    },
    "burst_frequency_fitness": {
        "Value": null,
        "Fit": 1000,
        "deprioritized": true
    },
    "big_burst_fit": {
        "Value": null,
        "Fit": 1000,
        "deprioritized": true
    },
    "small_burst_fit": {
        "Value": null,
        "Fit": 1000,
        "deprioritized": true
    },
    "thresh_fit": {
        "Value": 1490.450695626054,
        "Fit": 1000,
        "deprioritized": true
    },
    "bimodal_burst_fit": {
        "Value": null,
        "Fit": 1000,
        "deprioritized": true
    },
    "slope_fit": {
        "Value": -0.00011863277138200336,
        "Fit": 1000,
        "deprioritized": true
    },
    "maxFitness": 1000,
    "average_fitness": 1000.0,
    "average_scaled_fitness": 1.0
}