{
    "E_rate_fit": {
        "Value": 40.96403334303444,
        "Fit": 325.313859124559,
        "Features": {
            "E_rate_mean": 40.96403334303444,
            "E_rate_fitness": 940.0600812730684,
            "stdev": 49.00908312296555,
            "stdev_fitness": 1000,
            "kurtosis": 3.6029244257984,
            "kurtosis_fitness": 33.37891542013046,
            "skewness": 1.9353224716388135,
            "skew_fitness": 2.5025806804780557,
            "fitness": 325.313859124559
        }
    },
    "I_rate_fit": {
        "Value": 2.2912505453393877,
        "Fit": 218.13759411948172,
        "Features": {
            "I_rate_mean": 2.2912505453393877,
            "I_rate_fitness": 651.5118655264552,
            "stdev": 2.106803794160713,
            "stdev_fitness": 1.4212034447275792,
            "kurtosis": 2.640804705535275,
            "kurtosis_fitness": 1.766401561642529,
            "skewness": 1.567300396541298,
            "skew_fitness": 1.1345152703475399,
            "fitness": 218.13759411948172
        }
    },
    "E_ISI_fit": {
        "Value": 0.9275901810483127,
        "Fit": 658.027041662944,
        "Features": {
            "E_ISI_mean": 0.9275901810483127,
            "E_ISI_fitness": 940.0600533822834,
            "stdev": 2.349572461337911,
            "stdev_fitness": 5.478718239736044,
            "kurtosis": 17.168498472938076,
            "kurtosis_fitness": 1000,
            "skewness": 3.9915838200074467,
            "skew_fitness": 34.02107160654847,
            "fitness": 658.027041662944
        }
    },
    "I_ISI_fit": {
        "Value": 3.422843796772325,
        "Fit": 575.7472436978358,
        "Features": {
            "I_ISI_mean": 3.422843796772325,
            "I_ISI_fitness": 674.7445676876981,
            "stdev": 8.438142323188139,
            "stdev_fitness": 1000,
            "kurtosis": 18.06363373660827,
            "kurtosis_fitness": 1000,
            "skewness": 4.304947611730977,
            "skew_fitness": 52.49716340580897,
            "fitness": 575.7472436978358
        }
    },
    "baseline_fit": {
        "Value": 600.2608404965913,
        "Fit": 702.0714073198144
    },
    "IBI_fitness": {
        "Value": null,
        "Fit": 1000
    },
    "burst_frequency_fitness": {
        "Value": null,
        "Fit": 1000
    },
    "big_burst_fit": {
        "Value": 1392.7311396364248,
        "Fit": 500.5003195234994,
        "features": {
            "StdDev": 0.0,
            "Kurtosis": NaN,
            "Skewness": NaN,
            "StdDevFit": 1000,
            "KurtosisFit": NaN,
            "SkewnessFit": NaN
        }
    },
    "small_burst_fit": {
        "Value": null,
        "Fit": 1000
    },
    "thresh_fit": {
        "Value": 1204.2082552421766,
        "Fit": 1000
    },
    "bimodal_burst_fit": {
        "Value": null,
        "Fit": 1000
    },
    "slope_fit": {
        "Value": -0.0022873607730464,
        "Fit": 1.0017141066311062
    },
    "maxFitness": 1000,
    "average_fitness": 665.0665982962304,
    "average_scaled_fitness": 0.6647307543633566
}